matsengrp_meeting/__init__.py
matsengrp_meeting-0.1.0.dist-info/METADATA
matsengrp_meeting-0.1.0.dist-info/WHEEL
matsengrp_meeting-0.1.0.dist-info/RECORD
